huawei_solar_tools/__init__.py
huawei_solar_tools/devices/__init__.py
huawei_solar_tools/devices/battery.py
huawei_solar_tools/devices/device.py
huawei_solar_tools/devices/emi.py
huawei_solar_tools/devices/inverter.py
huawei_solar_tools/devices/meter.py
huawei_solar_tools/devices/power_meter.py
huawei_solar_tools/registers/__init__.py
huawei_solar_tools/registers/battery_register_names.py
huawei_solar_tools/registers/battery_registers.py
huawei_solar_tools/registers/emi_register_names.py
huawei_solar_tools/registers/emi_registers.py
huawei_solar_tools/registers/grid_codes.py
huawei_solar_tools/registers/inverter_register_names.py
huawei_solar_tools/registers/inverter_registers.py
huawei_solar_tools/registers/meter_register_names.py
huawei_solar_tools/registers/meter_registers.py
huawei_solar_tools/registers/power_meter_register_names.py
huawei_solar_tools/registers/power_meter_registers.py
huawei_solar_tools/tests/__init__.py
huawei_solar_tools/tests/test_battery.py
huawei_solar_tools/tests/test_data_send.py
huawei_solar_tools/tests/test_emi.py
huawei_solar_tools/tests/test_inverter.py
huawei_solar_tools/tests/test_meter.py
huawei_solar_tools/tests/test_power_meter.py
huawei_solar_tools/utils/__init__.py
huawei_solar_tools/utils/connection.py
huawei_solar_tools/utils/curve_processor.py
huawei_solar_tools/utils/generate_register_names.py
huawei_solar_tools/utils/register_interpreter.py
huawei_solar_tools-0.1.5.dist-info/licenses/LICENSE
huawei_solar_tools-0.1.5.dist-info/METADATA
huawei_solar_tools-0.1.5.dist-info/WHEEL
huawei_solar_tools-0.1.5.dist-info/top_level.txt
huawei_solar_tools-0.1.5.dist-info/RECORD
