Metadata-Version: 2.4
Name: huawei-solar-tools
Version: 0.1.5
Summary: A Python library for interacting with Huawei solar inverters, batteries, power meters, and EMI devices via Modbus TCP.
Home-page: https://github.com/atrabilis/huawei-solar-tools
Author: Angel Andrade
Author-email: angel.bruno.andrade.osorio@gmail.com
License: MIT
Project-URL: Documentation, https://github.com/atrabilis/huawei-solar-tools
Project-URL: Bug Tracker, https://github.com/atrabilis/huawei-solar-tools/issues
Project-URL: Source Code, https://github.com/atrabilis/huawei-solar-tools
Classifier: Development Status :: 4 - Beta
Classifier: Intended Audience :: Developers
Classifier: Intended Audience :: System Administrators
Classifier: Topic :: Scientific/Engineering :: Interface Engine/Protocol Translator
Classifier: Topic :: System :: Monitoring
Classifier: Topic :: Home Automation
Classifier: License :: OSI Approved :: MIT License
Classifier: Operating System :: OS Independent
Classifier: Programming Language :: Python :: 3
Classifier: Programming Language :: Python :: 3.9
Classifier: Programming Language :: Python :: 3.10
Classifier: Programming Language :: Python :: 3.11
Classifier: Programming Language :: Python :: 3.12
Requires-Python: >=3.9
License-File: LICENSE
Requires-Dist: pyModbusTCP
Provides-Extra: test
Requires-Dist: python-dotenv; extra == "test"
Requires-Dist: clickhouse-connect; extra == "test"
Requires-Dist: influxdb-client; extra == "test"
Requires-Dist: matplotlib; extra == "test"
Dynamic: license-file
